fetch_app/__init__.py
fetch_app/credentials.py
az_creds-0.0.6.dist-info/LICENSE
az_creds-0.0.6.dist-info/METADATA
az_creds-0.0.6.dist-info/WHEEL
az_creds-0.0.6.dist-info/entry_points.txt
az_creds-0.0.6.dist-info/top_level.txt
az_creds-0.0.6.dist-info/RECORD
