Metadata-Version: 2.1
Name: az-creds
Version: 0.0.6
Summary: UNKNOWN
Home-page: https://github.com/jilanisayyad/fetch_credentials
Author: Jilani Sayyad
Author-email: sayyedjilani88@gmail.com
License: GNU
Keywords: get_creds,fetch_credentials,azure,aks,azure-cli
Platform: UNKNOWN
License-File: LICENSE
Requires-Dist: simple-term-menu
Requires-Dist: pyyaml
